frozenjsondict/__init__.py
frozenjsondict-1.0.0.dist-info/LICENSE
frozenjsondict-1.0.0.dist-info/METADATA
frozenjsondict-1.0.0.dist-info/WHEEL
frozenjsondict-1.0.0.dist-info/top_level.txt
frozenjsondict-1.0.0.dist-info/RECORD
