Metadata-Version: 2.1
Name: frozenjsondict
Version: 1.0.0
Summary: Immutable JSON dictionary with hash functionality
Home-page: https://github.com/comprehensivetech/frozenjsondict
Author: Carlos Ruiz Lantero
Author-email: carlos.ruiz.lantero@comprehensivetech.co.uk
Maintainer: Carlos Ruiz Lantero
Maintainer-email: carlos.ruiz.lantero@comprehensivetech.co.uk
License: UNKNOWN
Platform: UNKNOWN
Classifier: Operating System :: OS Independent
Classifier: Programming Language :: Python
Classifier: Topic :: Software Development :: Libraries :: Python Modules
Provides-Extra: test
Requires-Dist: black (==20.8b1) ; extra == 'test'
Requires-Dist: flake8 (==3.9.0) ; extra == 'test'
Requires-Dist: pytest (==6.2.3) ; extra == 'test'
Requires-Dist: pytest-cov (==2.11.1) ; extra == 'test'
